lab3/top/top_module_counter_1.v
module counter_0_to_999 (
    input wire clk,       
    input wire reset,     
    output reg [9:0] count = 10'd0
);

    always @(posedge clk) begin
        if (reset)
            count <= 10'd0;           
        else if (count == 10'd999)
            count <= 10'd0;           
        else
            count <= count + 10'd1;  
    end

endmodule

lab3/top/top_module_counter_2.v
module shift_count_reg (
    input  wire       clk,        
    input  wire       shift_ena, 
    input  wire       count_ena,  
    input  wire       data,
    input  wire       reset, 
    output reg  [3:0] q          
);
    always @(posedge clk) begin
        if (reset) q <= 4'd0;
        if (shift_ena) begin
            // MSB first (старший бит уходит первым)
            q <= {q[2:0], data};
        end
        if (count_ena) begin
            q <= q - 1;
        end
    end

endmodule

lab3/top/top_module_counter_3.v
module sequence_detector_1101 (
    input  wire clk,
    input  wire reset,
    input  wire data,
    output reg  start_shifting
);

    // Определение состояний
    localparam S0 = 3'd0;
    localparam S1 = 3'd1;
    localparam S2 = 3'd2;
    localparam S3 = 3'd3;
    localparam S4 = 3'd4;

    reg [2:0] state, next_state;

    // Регистрация состояния
    always @(posedge clk) begin
        if (reset) begin
            state <= S0;
            start_shifting <= 1'b0;
        end else begin
            state <= next_state;
            if (next_state == S4) begin
                start_shifting <= 1'b1;
                state <= S0;
            end
        end
    end

    always @(*) begin
        case (state)
            S0: begin
                if (data == 1'b1) next_state = S1;
                else              next_state = S0;
            end
            S1: begin
                if (data == 1'b1) next_state = S2;
                else              next_state = S0;
            end
            S2: begin
                if (data == 1'b0) next_state = S3;
                else              next_state = S2;
            end
            S3: begin
                if (data == 1'b1) next_state = S4;
                else              next_state = S0;
            end
            S4: begin
                next_state = S4;
            end
            default: next_state = S0;
        endcase
    end

endmodule

lab3/top/top_top_module.v
module top_fsm (
    input  wire clk,
    input  wire reset,        
    input  wire data,
    input  wire ack,          

    output wire counting,
    output reg done
);

    localparam S_IDLE  = 2'd0;
    localparam S_SHIFT = 2'd1;
    localparam S_COUNT = 2'd2;
    localparam S_DONE  = 2'd3;

    wire start_shifting;
    wire [3:0] delay;
    reg shift_ena;
    reg count_ena;
    reg counter_done = 0;
    wire [9:0] counter999;


    reg [1:0] state, next_state;
    reg [3:0] repeat_cnt;       
    reg [3:0] delay_reg;        
    reg [1:0] shift_counter;    

    sequence_detector_1101 seq_det (
        .clk(clk),
        .reset(reset),
        .data(data),
        .start_shifting(start_shifting)
    );

    shift_count_reg shift_reg (
        .clk(clk),
        .shift_ena(shift_ena),
        .count_ena(count_ena),
        .data(data),
        .q(delay),
        .reset(reset)
    );

    counter_0_to_999 cnt_1k (
        .clk(clk),
        .reset(~count_ena),     // счётчик работает только при count_ena = 1
        .count(counter999)                
    );

    // counter_done = (counter999 == 10'd999);
    
    always @(posedge clk) begin
        if (reset) begin
            state        <= S_IDLE;
            repeat_cnt   <= 4'd0;
            delay_reg    <= 4'd0;
            shift_counter <= 2'd0;
        end else begin
            state <= next_state;

            case (state)
                S_SHIFT: begin
                    if (shift_counter == 2'd3) begin
                        delay_reg <= delay;
                    end else if (shift_counter < 2'd3) begin
                        shift_counter <= shift_counter + 1;
                    end else shift_counter <= 0;
                end
                S_COUNT: begin
                    if (counter999 == 10'd999) begin
                        repeat_cnt <= repeat_cnt + 1;
                    end
                end
                default: ;
            endcase
        end
    end

    always @(*) begin
        next_state = state;
        shift_ena  = 1'b0;
        count_ena  = 1'b0;

        case (state)
            S_IDLE: begin
                if (start_shifting) begin
                    next_state = S_SHIFT;
                end
            end

            S_SHIFT: begin
                shift_ena = 1'b1;
                if (shift_counter == 2'd3) begin
                    next_state = S_COUNT;
                end
            end

            S_COUNT: begin
                count_ena = 1'b1;
                if (repeat_cnt == delay_reg) begin
                    next_state = S_DONE;
                end
            end

            S_DONE: begin
                if (ack) begin
                    next_state = S_IDLE;
                end
            end

            default: next_state = S_IDLE;
        endcase
    end

    assign counting = (state == S_COUNT);
    assign done = (state == S_DONE);

endmodule

lab3/top/top_top_module_tb.v
`timescale 1ns/1ps
module top_fsm_tb;

    reg clk = 1;
    always #5 clk = ~clk;

    reg reset = 1; reg ack = 0;  
    reg count[3:0]; reg data = 0;
    wire done;
    wire counting;

    top_fsm FSM(
        .clk(clk),
        .reset(reset),
        .ack(ack),
        .data(data),
        .counting(counting),
        .done(done)
    );
    
    initial begin
        $dumpfile("final.vcd");
		$dumpvars(0, top_fsm_tb);
        $display("-----------------------------");
        #20 
        reset = 0; data = 1;    //10
        
        #10                     //20
        data = 0;
        
        #20                     //40
        data = 1;

        #20                     //60
        data = 0;               

        #10
        data = 1;               //70

        #10
        data = 0;               //80

        #30
        data = 1;               //110

        #15000
        #400
        $display("-----------------------------");
        $finish;
    end

endmodule

lab3/final.vcd
$date
	Tue Nov  4 22:13:25 2025
$end
$version
	Icarus Verilog
$end
$timescale
	1ps
$end
$scope module top_fsm_tb $end
$var wire 1 ! done $end
$var wire 1 " counting $end
$var reg 1 # ack $end
$var reg 1 $ clk $end
$var reg 1 % data $end
$var reg 1 & reset $end
$scope module FSM $end
$var wire 1 # ack $end
$var wire 1 $ clk $end
$var wire 1 % data $end
$var wire 1 & reset $end
$var wire 1 ' start_shifting $end
$var wire 1 ! done $end
$var wire 4 ( delay [3:0] $end
$var wire 1 " counting $end
$var wire 10 ) counter999 [9:0] $end
$var parameter 2 * S_COUNT $end
$var parameter 2 + S_DONE $end
$var parameter 2 , S_IDLE $end
$var parameter 2 - S_SHIFT $end
$var reg 1 . count_ena $end
$var reg 1 / counter_done $end
$var reg 4 0 delay_reg [3:0] $end
$var reg 2 1 next_state [1:0] $end
$var reg 4 2 repeat_cnt [3:0] $end
$var reg 2 3 shift_counter [1:0] $end
$var reg 1 4 shift_ena $end
$var reg 2 5 state [1:0] $end
$scope module cnt_1k $end
$var wire 1 $ clk $end
$var wire 1 6 reset $end
$var reg 10 7 count [9:0] $end
$upscope $end
$scope module seq_det $end
$var wire 1 $ clk $end
$var wire 1 % data $end
$var wire 1 & reset $end
$var parameter 3 8 S0 $end
$var parameter 3 9 S1 $end
$var parameter 3 : S2 $end
$var parameter 3 ; S3 $end
$var parameter 3 < S4 $end
$var reg 3 = next_state [2:0] $end
$var reg 1 ' start_shifting $end
$var reg 3 > state [2:0] $end
$upscope $end
$scope module shift_reg $end
$var wire 1 $ clk $end
$var wire 1 . count_ena $end
$var wire 1 % data $end
$var wire 1 & reset $end
$var wire 1 4 shift_ena $end
$var reg 4 ? q [3:0] $end
$upscope $end
$upscope $end
$upscope $end
$enddefinitions $end
$comment Show the parameter values. $end
$dumpall
b100 <
b11 ;
b10 :
b1 9
b0 8
b1 -
b0 ,
b11 +
b10 *
$end
#0
$dumpvars
bx ?
bx >
bx =
b0 7
x6
bx 5
x4
bx 3
bx 2
bx 1
bx 0
0/
x.
b0 )
bx (
x'
1&
0%
1$
0#
x"
x!
$end
#5000
0$
#10000
16
b0 =
0.
04
b0 1
0'
b0 >
b0 (
b0 ?
b1 )
b1 7
b0 3
b0 0
b0 2
0"
0!
b0 5
1$
#15000
0$
#20000
b0 )
b0 7
b1 >
b10 =
1$
1%
0&
#25000
0$
#30000
b0 >
b0 =
1$
0%
#35000
0$
#40000
1$
#45000
0$
#50000
b1 >
b10 =
1$
1%
#55000
0$
#60000
b10 >
1$
#65000
0$
#70000
b11 >
b0 =
1$
0%
#75000
0$
#80000
b1 1
1'
b0 >
b1 =
1$
1%
#85000
0$
#90000
14
b1 5
b0 =
1$
0%
#95000
0$
#100000
14
b1 3
1$
#105000
0$
#110000
14
b10 3
1$
#115000
0$
#120000
b10 1
14
b11 3
b1 (
b1 ?
b1 >
b10 =
1$
1%
#125000
0$
#130000
06
1.
04
b10 >
b11 (
b11 ?
b1 0
1"
b10 5
1$
#135000
0$
#140000
b1 )
b1 7
b10 (
b10 ?
1$
#145000
0$
#150000
b1 (
b1 ?
b10 )
b10 7
1$
#155000
0$
#160000
b11 )
b11 7
b0 (
b0 ?
1$
#165000
0$
#170000
b1111 (
b1111 ?
b100 )
b100 7
1$
#175000
0$
#180000
b101 )
b101 7
b1110 (
b1110 ?
1$
#185000
0$
#190000
b1101 (
b1101 ?
b110 )
b110 7
1$
#195000
0$
#200000
b111 )
b111 7
b1100 (
b1100 ?
1$
#205000
0$
#210000
b1011 (
b1011 ?
b1000 )
b1000 7
1$
#215000
0$
#220000
b1001 )
b1001 7
b1010 (
b1010 ?
1$
#225000
0$
#230000
b1001 (
b1001 ?
b1010 )
b1010 7
1$
#235000
0$
#240000
b1011 )
b1011 7
b1000 (
b1000 ?
1$
#245000
0$
#250000
b111 (
b111 ?
b1100 )
b1100 7
1$
#255000
0$
#260000
b1101 )
b1101 7
b110 (
b110 ?
1$
#265000
0$
#270000
b101 (
b101 ?
b1110 )
b1110 7
1$
#275000
0$
#280000
b1111 )
b1111 7
b100 (
b100 ?
1$
#285000
0$
#290000
b11 (
b11 ?
b10000 )
b10000 7
1$
#295000
0$
#300000
b10001 )
b10001 7
b10 (
b10 ?
1$
#305000
0$
#310000
b1 (
b1 ?
b10010 )
b10010 7
1$
#315000
0$
#320000
b10011 )
b10011 7
b0 (
b0 ?
1$
#325000
0$
#330000
b1111 (
b1111 ?
b10100 )
b10100 7
1$
#335000
0$
#340000
b10101 )
b10101 7
b1110 (
b1110 ?
1$
#345000
0$
#350000
b1101 (
b1101 ?
b10110 )
b10110 7
1$
#355000
0$
#360000
b10111 )
b10111 7
b1100 (
b1100 ?
1$
#365000
0$
#370000
b1011 (
b1011 ?
b11000 )
b11000 7
1$
#375000
0$
#380000
b11001 )
b11001 7
b1010 (
b1010 ?
1$
#385000
0$
#390000
b1001 (
b1001 ?
b11010 )
b11010 7
1$
#395000
0$
#400000
b11011 )
b11011 7
b1000 (
b1000 ?
1$
#405000
0$
#410000
b111 (
b111 ?
b11100 )
b11100 7
1$
#415000
0$
#420000
b11101 )
b11101 7
b110 (
b110 ?
1$
#425000
0$
#430000
b101 (
b101 ?
b11110 )
b11110 7
1$
#435000
0$
#440000
b11111 )
b11111 7
b100 (
b100 ?
1$
#445000
0$
#450000
b11 (
b11 ?
b100000 )
b100000 7
1$
#455000
0$
#460000
b100001 )
b100001 7
b10 (
b10 ?
1$
#465000
0$
#470000
b1 (
b1 ?
b100010 )
b100010 7
1$
#475000
0$
#480000
b100011 )
b100011 7
b0 (
b0 ?
1$
#485000
0$
#490000
b1111 (
b1111 ?
b100100 )
b100100 7
1$
#495000
0$
#500000
b100101 )
b100101 7
b1110 (
b1110 ?
1$
#505000
0$
#510000
b1101 (
b1101 ?
b100110 )
b100110 7
1$
#515000
0$
#520000
b100111 )
b100111 7
b1100 (
b1100 ?
1$
#525000
0$
#530000
b1011 (
b1011 ?
b101000 )
b101000 7
1$
#535000
0$
#540000
b101001 )
b101001 7
b1010 (
b1010 ?
1$
#545000
0$
#550000
b1001 (
b1001 ?
b101010 )
b101010 7
1$
#555000
0$
#560000
b101011 )
b101011 7
b1000 (
b1000 ?
1$
#565000
0$
#570000
b111 (
b111 ?
b101100 )
b101100 7
1$
#575000
0$
#580000
b101101 )
b101101 7
b110 (
b110 ?
1$
#585000
0$
#590000
b101 (
b101 ?
b101110 )
b101110 7
1$
#595000
0$
#600000
b101111 )
b101111 7
b100 (
b100 ?
1$
#605000
0$
#610000
b11 (
b11 ?
b110000 )
b110000 7
1$
#615000
0$
#620000
b110001 )
b110001 7
b10 (
b10 ?
1$
#625000
0$
#630000
b1 (
b1 ?
b110010 )
b110010 7
1$
#635000
0$
#640000
b110011 )
b110011 7
b0 (
b0 ?
1$
#645000
0$
#650000
b1111 (
b1111 ?
b110100 )
b110100 7
1$
#655000
0$
#660000
b110101 )
b110101 7
b1110 (
b1110 ?
1$
#665000
0$
#670000
b1101 (
b1101 ?
b110110 )
b110110 7
1$
#675000
0$
#680000
b110111 )
b110111 7
b1100 (
b1100 ?
1$
#685000
0$
#690000
b1011 (
b1011 ?
b111000 )
b111000 7
1$
#695000
0$
#700000
b111001 )
b111001 7
b1010 (
b1010 ?
1$
#705000
0$
#710000
b1001 (
b1001 ?
b111010 )
b111010 7
1$
#715000
0$
#720000
b111011 )
b111011 7
b1000 (
b1000 ?
1$
#725000
0$
#730000
b111 (
b111 ?
b111100 )
b111100 7
1$
#735000
0$
#740000
b111101 )
b111101 7
b110 (
b110 ?
1$
#745000
0$
#750000
b101 (
b101 ?
b111110 )
b111110 7
1$
#755000
0$
#760000
b111111 )
b111111 7
b100 (
b100 ?
1$
#765000
0$
#770000
b11 (
b11 ?
b1000000 )
b1000000 7
1$
#775000
0$
#780000
b1000001 )
b1000001 7
b10 (
b10 ?
1$
#785000
0$
#790000
b1 (
b1 ?
b1000010 )
b1000010 7
1$
#795000
0$
#800000
b1000011 )
b1000011 7
b0 (
b0 ?
1$
#805000
0$
#810000
b1111 (
b1111 ?
b1000100 )
b1000100 7
1$
#815000
0$
#820000
b1000101 )
b1000101 7
b1110 (
b1110 ?
1$
#825000
0$
#830000
b1101 (
b1101 ?
b1000110 )
b1000110 7
1$
#835000
0$
#840000
b1000111 )
b1000111 7
b1100 (
b1100 ?
1$
#845000
0$
#850000
b1011 (
b1011 ?
b1001000 )
b1001000 7
1$
#855000
0$
#860000
b1001001 )
b1001001 7
b1010 (
b1010 ?
1$
#865000
0$
#870000
b1001 (
b1001 ?
b1001010 )
b1001010 7
1$
#875000
0$
#880000
b1001011 )
b1001011 7
b1000 (
b1000 ?
1$
#885000
0$
#890000
b111 (
b111 ?
b1001100 )
b1001100 7
1$
#895000
0$
#900000
b1001101 )
b1001101 7
b110 (
b110 ?
1$
#905000
0$
#910000
b101 (
b101 ?
b1001110 )
b1001110 7
1$
#915000
0$
#920000
b1001111 )
b1001111 7
b100 (
b100 ?
1$
#925000
0$
#930000
b11 (
b11 ?
b1010000 )
b1010000 7
1$
#935000
0$
#940000
b1010001 )
b1010001 7
b10 (
b10 ?
1$
#945000
0$
#950000
b1 (
b1 ?
b1010010 )
b1010010 7
1$
#955000
0$
#960000
b1010011 )
b1010011 7
b0 (
b0 ?
1$
#965000
0$
#970000
b1111 (
b1111 ?
b1010100 )
b1010100 7
1$
#975000
0$
#980000
b1010101 )
b1010101 7
b1110 (
b1110 ?
1$
#985000
0$
#990000
b1101 (
b1101 ?
b1010110 )
b1010110 7
1$
#995000
0$
#1000000
b1010111 )
b1010111 7
b1100 (
b1100 ?
1$
#1005000
0$
#1010000
b1011 (
b1011 ?
b1011000 )
b1011000 7
1$
#1015000
0$
#1020000
b1011001 )
b1011001 7
b1010 (
b1010 ?
1$
#1025000
0$
#1030000
b1001 (
b1001 ?
b1011010 )
b1011010 7
1$
#1035000
0$
#1040000
b1011011 )
b1011011 7
b1000 (
b1000 ?
1$
#1045000
0$
#1050000
b111 (
b111 ?
b1011100 )
b1011100 7
1$
#1055000
0$
#1060000
b1011101 )
b1011101 7
b110 (
b110 ?
1$
#1065000
0$
#1070000
b101 (
b101 ?
b1011110 )
b1011110 7
1$
#1075000
0$
#1080000
b1011111 )
b1011111 7
b100 (
b100 ?
1$
#1085000
0$
#1090000
b11 (
b11 ?
b1100000 )
b1100000 7
1$
#1095000
0$
#1100000
b1100001 )
b1100001 7
b10 (
b10 ?
1$
#1105000
0$
#1110000
b1 (
b1 ?
b1100010 )
b1100010 7
1$
#1115000
0$
#1120000
b1100011 )
b1100011 7
b0 (
b0 ?
1$
#1125000
0$
#1130000
b1111 (
b1111 ?
b1100100 )
b1100100 7
1$
#1135000
0$
#1140000
b1100101 )
b1100101 7
b1110 (
b1110 ?
1$
#1145000
0$
#1150000
b1101 (
b1101 ?
b1100110 )
b1100110 7
1$
#1155000
0$
#1160000
b1100111 )
b1100111 7
b1100 (
b1100 ?
1$
#1165000
0$
#1170000
b1011 (
b1011 ?
b1101000 )
b1101000 7
1$
#1175000
0$
#1180000
b1101001 )
b1101001 7
b1010 (
b1010 ?
1$
#1185000
0$
#1190000
b1001 (
b1001 ?
b1101010 )
b1101010 7
1$
#1195000
0$
#1200000
b1101011 )
b1101011 7
b1000 (
b1000 ?
1$
#1205000
0$
#1210000
b111 (
b111 ?
b1101100 )
b1101100 7
1$
#1215000
0$
#1220000
b1101101 )
b1101101 7
b110 (
b110 ?
1$
#1225000
0$
#1230000
b101 (
b101 ?
b1101110 )
b1101110 7
1$
#1235000
0$
#1240000
b1101111 )
b1101111 7
b100 (
b100 ?
1$
#1245000
0$
#1250000
b11 (
b11 ?
b1110000 )
b1110000 7
1$
#1255000
0$
#1260000
b1110001 )
b1110001 7
b10 (
b10 ?
1$
#1265000
0$
#1270000
b1 (
b1 ?
b1110010 )
b1110010 7
1$
#1275000
0$
#1280000
b1110011 )
b1110011 7
b0 (
b0 ?
1$
#1285000
0$
#1290000
b1111 (
b1111 ?
b1110100 )
b1110100 7
1$
#1295000
0$
#1300000
b1110101 )
b1110101 7
b1110 (
b1110 ?
1$
#1305000
0$
#1310000
b1101 (
b1101 ?
b1110110 )
b1110110 7
1$
#1315000
0$
#1320000
b1110111 )
b1110111 7
b1100 (
b1100 ?
1$
#1325000
0$
#1330000
b1011 (
b1011 ?
b1111000 )
b1111000 7
1$
#1335000
0$
#1340000
b1111001 )
b1111001 7
b1010 (
b1010 ?
1$
#1345000
0$
#1350000
b1001 (
b1001 ?
b1111010 )
b1111010 7
1$
#1355000
0$
#1360000
b1111011 )
b1111011 7
b1000 (
b1000 ?
1$
#1365000
0$
#1370000
b111 (
b111 ?
b1111100 )
b1111100 7
1$
#1375000
0$
#1380000
b1111101 )
b1111101 7
b110 (
b110 ?
1$
#1385000
0$
#1390000
b101 (
b101 ?
b1111110 )
b1111110 7
1$
#1395000
0$
#1400000
b1111111 )
b1111111 7
b100 (
b100 ?
1$
#1405000
0$
#1410000
b11 (
b11 ?
b10000000 )
b10000000 7
1$
#1415000
0$
#1420000
b10000001 )
b10000001 7
b10 (
b10 ?
1$
#1425000
0$
#1430000
b1 (
b1 ?
b10000010 )
b10000010 7
1$
#1435000
0$
#1440000
b10000011 )
b10000011 7
b0 (
b0 ?
1$
#1445000
0$
#1450000
b1111 (
b1111 ?
b10000100 )
b10000100 7
1$
#1455000
0$
#1460000
b10000101 )
b10000101 7
b1110 (
b1110 ?
1$
#1465000
0$
#1470000
b1101 (
b1101 ?
b10000110 )
b10000110 7
1$
#1475000
0$
#1480000
b10000111 )
b10000111 7
b1100 (
b1100 ?
1$
#1485000
0$
#1490000
b1011 (
b1011 ?
b10001000 )
b10001000 7
1$
#1495000
0$
#1500000
b10001001 )
b10001001 7
b1010 (
b1010 ?
1$
#1505000
0$
#1510000
b1001 (
b1001 ?
b10001010 )
b10001010 7
1$
#1515000
0$
#1520000
b10001011 )
b10001011 7
b1000 (
b1000 ?
1$
#1525000
0$
#1530000
b111 (
b111 ?
b10001100 )
b10001100 7
1$
#1535000
0$
#1540000
b10001101 )
b10001101 7
b110 (
b110 ?
1$
#1545000
0$
#1550000
b101 (
b101 ?
b10001110 )
b10001110 7
1$
#1555000
0$
#1560000
b10001111 )
b10001111 7
b100 (
b100 ?
1$
#1565000
0$
#1570000
b11 (
b11 ?
b10010000 )
b10010000 7
1$
#1575000
0$
#1580000
b10010001 )
b10010001 7
b10 (
b10 ?
1$
#1585000
0$
#1590000
b1 (
b1 ?
b10010010 )
b10010010 7
1$
#1595000
0$
#1600000
b10010011 )
b10010011 7
b0 (
b0 ?
1$
#1605000
0$
#1610000
b1111 (
b1111 ?
b10010100 )
b10010100 7
1$
#1615000
0$
#1620000
b10010101 )
b10010101 7
b1110 (
b1110 ?
1$
#1625000
0$
#1630000
b1101 (
b1101 ?
b10010110 )
b10010110 7
1$
#1635000
0$
#1640000
b10010111 )
b10010111 7
b1100 (
b1100 ?
1$
#1645000
0$
#1650000
b1011 (
b1011 ?
b10011000 )
b10011000 7
1$
#1655000
0$
#1660000
b10011001 )
b10011001 7
b1010 (
b1010 ?
1$
#1665000
0$
#1670000
b1001 (
b1001 ?
b10011010 )
b10011010 7
1$
#1675000
0$
#1680000
b10011011 )
b10011011 7
b1000 (
b1000 ?
1$
#1685000
0$
#1690000
b111 (
b111 ?
b10011100 )
b10011100 7
1$
#1695000
0$
#1700000
b10011101 )
b10011101 7
b110 (
b110 ?
1$
#1705000
0$
#1710000
b101 (
b101 ?
b10011110 )
b10011110 7
1$
#1715000
0$
#1720000
b10011111 )
b10011111 7
b100 (
b100 ?
1$
#1725000
0$
#1730000
b11 (
b11 ?
b10100000 )
b10100000 7
1$
#1735000
0$
#1740000
b10100001 )
b10100001 7
b10 (
b10 ?
1$
#1745000
0$
#1750000
b1 (
b1 ?
b10100010 )
b10100010 7
1$
#1755000
0$
#1760000
b10100011 )
b10100011 7
b0 (
b0 ?
1$
#1765000
0$
#1770000
b1111 (
b1111 ?
b10100100 )
b10100100 7
1$
#1775000
0$
#1780000
b10100101 )
b10100101 7
b1110 (
b1110 ?
1$
#1785000
0$
#1790000
b1101 (
b1101 ?
b10100110 )
b10100110 7
1$
#1795000
0$
#1800000
b10100111 )
b10100111 7
b1100 (
b1100 ?
1$
#1805000
0$
#1810000
b1011 (
b1011 ?
b10101000 )
b10101000 7
1$
#1815000
0$
#1820000
b10101001 )
b10101001 7
b1010 (
b1010 ?
1$
#1825000
0$
#1830000
b1001 (
b1001 ?
b10101010 )
b10101010 7
1$
#1835000
0$
#1840000
b10101011 )
b10101011 7
b1000 (
b1000 ?
1$
#1845000
0$
#1850000
b111 (
b111 ?
b10101100 )
b10101100 7
1$
#1855000
0$
#1860000
b10101101 )
b10101101 7
b110 (
b110 ?
1$
#1865000
0$
#1870000
b101 (
b101 ?
b10101110 )
b10101110 7
1$
#1875000
0$
#1880000
b10101111 )
b10101111 7
b100 (
b100 ?
1$
#1885000
0$
#1890000
b11 (
b11 ?
b10110000 )
b10110000 7
1$
#1895000
0$
#1900000
b10110001 )
b10110001 7
b10 (
b10 ?
1$
#1905000
0$
#1910000
b1 (
b1 ?
b10110010 )
b10110010 7
1$
#1915000
0$
#1920000
b10110011 )
b10110011 7
b0 (
b0 ?
1$
#1925000
0$
#1930000
b1111 (
b1111 ?
b10110100 )
b10110100 7
1$
#1935000
0$
#1940000
b10110101 )
b10110101 7
b1110 (
b1110 ?
1$
#1945000
0$
#1950000
b1101 (
b1101 ?
b10110110 )
b10110110 7
1$
#1955000
0$
#1960000
b10110111 )
b10110111 7
b1100 (
b1100 ?
1$
#1965000
0$
#1970000
b1011 (
b1011 ?
b10111000 )
b10111000 7
1$
#1975000
0$
#1980000
b10111001 )
b10111001 7
b1010 (
b1010 ?
1$
#1985000
0$
#1990000
b1001 (
b1001 ?
b10111010 )
b10111010 7
1$
#1995000
0$
#2000000
b10111011 )
b10111011 7
b1000 (
b1000 ?
1$
#2005000
0$
#2010000
b111 (
b111 ?
b10111100 )
b10111100 7
1$
#2015000
0$
#2020000
b10111101 )
b10111101 7
b110 (
b110 ?
1$
#2025000
0$
#2030000
b101 (
b101 ?
b10111110 )
b10111110 7
1$
#2035000
0$
#2040000
b10111111 )
b10111111 7
b100 (
b100 ?
1$
#2045000
0$
#2050000
b11 (
b11 ?
b11000000 )
b11000000 7
1$
#2055000
0$
#2060000
b11000001 )
b11000001 7
b10 (
b10 ?
1$
#2065000
0$
#2070000
b1 (
b1 ?
b11000010 )
b11000010 7
1$
#2075000
0$
#2080000
b11000011 )
b11000011 7
b0 (
b0 ?
1$
#2085000
0$
#2090000
b1111 (
b1111 ?
b11000100 )
b11000100 7
1$
#2095000
0$
#2100000
b11000101 )
b11000101 7
b1110 (
b1110 ?
1$
#2105000
0$
#2110000
b1101 (
b1101 ?
b11000110 )
b11000110 7
1$
#2115000
0$
#2120000
b11000111 )
b11000111 7
b1100 (
b1100 ?
1$
#2125000
0$
#2130000
b1011 (
b1011 ?
b11001000 )
b11001000 7
1$
#2135000
0$
#2140000
b11001001 )
b11001001 7
b1010 (
b1010 ?
1$
#2145000
0$
#2150000
b1001 (
b1001 ?
b11001010 )
b11001010 7
1$
#2155000
0$
#2160000
b11001011 )
b11001011 7
b1000 (
b1000 ?
1$
#2165000
0$
#2170000
b111 (
b111 ?
b11001100 )
b11001100 7
1$
#2175000
0$
#2180000
b11001101 )
b11001101 7
b110 (
b110 ?
1$
#2185000
0$
#2190000
b101 (
b101 ?
b11001110 )
b11001110 7
1$
#2195000
0$
#2200000
b11001111 )
b11001111 7
b100 (
b100 ?
1$
#2205000
0$
#2210000
b11 (
b11 ?
b11010000 )
b11010000 7
1$
#2215000
0$
#2220000
b11010001 )
b11010001 7
b10 (
b10 ?
1$
#2225000
0$
#2230000
b1 (
b1 ?
b11010010 )
b11010010 7
1$
#2235000
0$
#2240000
b11010011 )
b11010011 7
b0 (
b0 ?
1$
#2245000
0$
#2250000
b1111 (
b1111 ?
b11010100 )
b11010100 7
1$
#2255000
0$
#2260000
b11010101 )
b11010101 7
b1110 (
b1110 ?
1$
#2265000
0$
#2270000
b1101 (
b1101 ?
b11010110 )
b11010110 7
1$
#2275000
0$
#2280000
b11010111 )
b11010111 7
b1100 (
b1100 ?
1$
#2285000
0$
#2290000
b1011 (
b1011 ?
b11011000 )
b11011000 7
1$
#2295000
0$
#2300000
b11011001 )
b11011001 7
b1010 (
b1010 ?
1$
#2305000
0$
#2310000
b1001 (
b1001 ?
b11011010 )
b11011010 7
1$
#2315000
0$
#2320000
b11011011 )
b11011011 7
b1000 (
b1000 ?
1$
#2325000
0$
#2330000
b111 (
b111 ?
b11011100 )
b11011100 7
1$
#2335000
0$
#2340000
b11011101 )
b11011101 7
b110 (
b110 ?
1$
#2345000
0$
#2350000
b101 (
b101 ?
b11011110 )
b11011110 7
1$
#2355000
0$
#2360000
b11011111 )
b11011111 7
b100 (
b100 ?
1$
#2365000
0$
#2370000
b11 (
b11 ?
b11100000 )
b11100000 7
1$
#2375000
0$
#2380000
b11100001 )
b11100001 7
b10 (
b10 ?
1$
#2385000
0$
#2390000
b1 (
b1 ?
b11100010 )
b11100010 7
1$
#2395000
0$
#2400000
b11100011 )
b11100011 7
b0 (
b0 ?
1$
#2405000
0$
#2410000
b1111 (
b1111 ?
b11100100 )
b11100100 7
1$
#2415000
0$
#2420000
b11100101 )
b11100101 7
b1110 (
b1110 ?
1$
#2425000
0$
#2430000
b1101 (
b1101 ?
b11100110 )
b11100110 7
1$
#2435000
0$
#2440000
b11100111 )
b11100111 7
b1100 (
b1100 ?
1$
#2445000
0$
#2450000
b1011 (
b1011 ?
b11101000 )
b11101000 7
1$
#2455000
0$
#2460000
b11101001 )
b11101001 7
b1010 (
b1010 ?
1$
#2465000
0$
#2470000
b1001 (
b1001 ?
b11101010 )
b11101010 7
1$
#2475000
0$
#2480000
b11101011 )
b11101011 7
b1000 (
b1000 ?
1$
#2485000
0$
#2490000
b111 (
b111 ?
b11101100 )
b11101100 7
1$
#2495000
0$
#2500000
b11101101 )
b11101101 7
b110 (
b110 ?
1$
#2505000
0$
#2510000
b101 (
b101 ?
b11101110 )
b11101110 7
1$
#2515000
0$
#2520000
b11101111 )
b11101111 7
b100 (
b100 ?
1$
#2525000
0$
#2530000
b11 (
b11 ?
b11110000 )
b11110000 7
1$
#2535000
0$
#2540000
b11110001 )
b11110001 7
b10 (
b10 ?
1$
#2545000
0$
#2550000
b1 (
b1 ?
b11110010 )
b11110010 7
1$
#2555000
0$
#2560000
b11110011 )
b11110011 7
b0 (
b0 ?
1$
#2565000
0$
#2570000
b1111 (
b1111 ?
b11110100 )
b11110100 7
1$
#2575000
0$
#2580000
b11110101 )
b11110101 7
b1110 (
b1110 ?
1$
#2585000
0$
#2590000
b1101 (
b1101 ?
b11110110 )
b11110110 7
1$
#2595000
0$
#2600000
b11110111 )
b11110111 7
b1100 (
b1100 ?
1$
#2605000
0$
#2610000
b1011 (
b1011 ?
b11111000 )
b11111000 7
1$
#2615000
0$
#2620000
b11111001 )
b11111001 7
b1010 (
b1010 ?
1$
#2625000
0$
#2630000
b1001 (
b1001 ?
b11111010 )
b11111010 7
1$
#2635000
0$
#2640000
b11111011 )
b11111011 7
b1000 (
b1000 ?
1$
#2645000
0$
#2650000
b111 (
b111 ?
b11111100 )
b11111100 7
1$
#2655000
0$
#2660000
b11111101 )
b11111101 7
b110 (
b110 ?
1$
#2665000
0$
#2670000
b101 (
b101 ?
b11111110 )
b11111110 7
1$
#2675000
0$
#2680000
b11111111 )
b11111111 7
b100 (
b100 ?
1$
#2685000
0$
#2690000
b11 (
b11 ?
b100000000 )
b100000000 7
1$
#2695000
0$
#2700000
b100000001 )
b100000001 7
b10 (
b10 ?
1$
#2705000
0$
#2710000
b1 (
b1 ?
b100000010 )
b100000010 7
1$
#2715000
0$
#2720000
b100000011 )
b100000011 7
b0 (
b0 ?
1$
#2725000
0$
#2730000
b1111 (
b1111 ?
b100000100 )
b100000100 7
1$
#2735000
0$
#2740000
b100000101 )
b100000101 7
b1110 (
b1110 ?
1$
#2745000
0$
#2750000
b1101 (
b1101 ?
b100000110 )
b100000110 7
1$
#2755000
0$
#2760000
b100000111 )
b100000111 7
b1100 (
b1100 ?
1$
#2765000
0$
#2770000
b1011 (
b1011 ?
b100001000 )
b100001000 7
1$
#2775000
0$
#2780000
b100001001 )
b100001001 7
b1010 (
b1010 ?
1$
#2785000
0$
#2790000
b1001 (
b1001 ?
b100001010 )
b100001010 7
1$
#2795000
0$
#2800000
b100001011 )
b100001011 7
b1000 (
b1000 ?
1$
#2805000
0$
#2810000
b111 (
b111 ?
b100001100 )
b100001100 7
1$
#2815000
0$
#2820000
b100001101 )
b100001101 7
b110 (
b110 ?
1$
#2825000
0$
#2830000
b101 (
b101 ?
b100001110 )
b100001110 7
1$
#2835000
0$
#2840000
b100001111 )
b100001111 7
b100 (
b100 ?
1$
#2845000
0$
#2850000
b11 (
b11 ?
b100010000 )
b100010000 7
1$
