lab3/top/top_module_counter_3.v
module sequence_detector_1101 (
    input  wire clk,
    input  wire reset,
    input  wire data,
    output reg  start_shifting
);

    // Определение состояний
    localparam S0 = 3'd0;
    localparam S1 = 3'd1;
    localparam S2 = 3'd2;
    localparam S3 = 3'd3;
    localparam S4 = 3'd4;

    reg [2:0] state, next_state;

    // Регистрация состояния
    always @(posedge clk) begin
        if (reset) begin
            state <= S0;
            start_shifting <= 1'b0;
        end else begin
            state <= next_state;
            if (next_state == S4) begin
                start_shifting <= 1'b1;
                state <= S0;
            end
        end
    end

    always @(*) begin
        case (state)
            S0: begin
                if (data == 1'b1) next_state = S1;
                else              next_state = S0;
            end
            S1: begin
                if (data == 1'b1) next_state = S2;
                else              next_state = S0;
            end
            S2: begin
                if (data == 1'b0) next_state = S3;
                else              next_state = S2;
            end
            S3: begin
                if (data == 1'b1) next_state = S4;
                else              next_state = S0;
            end
            S4: begin
                next_state = S4;
            end
            default: next_state = S0;
        endcase
    end

endmodule

lab3/top_module_counter_3_tb.v
`timescale 1ns / 1ps

module tb_sequence_detector_1101;

    reg clk;
    reg reset;
    reg data;
    wire start_shifting;

    sequence_detector_1101 fsm (
        .clk(clk),
        .reset(reset),
        .data(data),
        .start_shifting(start_shifting)
    );

    always #5 clk = ~clk;

    initial begin
        $dumpfile("fsm_mini.vcd");
		$dumpvars(0, tb_sequence_detector_1101);

        clk = 0;
        reset = 1;
        data = 0;
        #10 reset = 0;      //10
        
        #10 data = 1;       //20
        
        #10 data = 0;       //30
        
        #10 data = 1;       //40
        
        #50 data = 0;       //90
        
        #10 data = 1;       //100
        
        #20 data = 0;       //120
        
        #20 data = 1; 
        reset = 1;          //140
        
        #40
        $display("Simulation finished.");
        $finish;
    end
endmodule

lab3/fsm_mini.vcd
$date
	Tue Nov  4 19:10:28 2025
$end
$version
	Icarus Verilog
$end
$timescale
	1ps
$end
$scope module tb_sequence_detector_1101 $end
$var wire 1 ! start_shifting $end
$var reg 1 " clk $end
$var reg 1 # data $end
$var reg 1 $ reset $end
$scope module fsm $end
$var wire 1 " clk $end
$var wire 1 # data $end
$var wire 1 $ reset $end
$var parameter 3 % S0 $end
$var parameter 3 & S1 $end
$var parameter 3 ' S2 $end
$var parameter 3 ( S3 $end
$var parameter 3 ) S4 $end
$var reg 3 * next_state [2:0] $end
$var reg 1 ! start_shifting $end
$var reg 3 + state [2:0] $end
$upscope $end
$upscope $end
$enddefinitions $end
$comment Show the parameter values. $end
$dumpall
b100 )
b11 (
b10 '
b1 &
b0 %
$end
#0
$dumpvars
bx +
b0 *
1$
0#
0"
x!
$end
#5000
0!
b0 +
1"
#10000
0"
0$
#15000
1"
#20000
b1 *
0"
1#
#25000
b10 *
b1 +
1"
#30000
b0 *
0"
0#
#35000
b0 +
1"
#40000
b1 *
0"
1#
#45000
b10 *
b1 +
1"
#50000
0"
#55000
b10 +
1"
#60000
0"
#65000
1"
#70000
0"
#75000
1"
#80000
0"
#85000
1"
#90000
b11 *
0"
0#
#95000
b0 *
b11 +
1"
#100000
b100 *
0"
1#
#105000
b1 *
1!
b0 +
1"
#110000
0"
#115000
b10 *
b1 +
1"
#120000
b0 *
0"
0#
#125000
b0 +
1"
#130000
0"
#135000
1"
#140000
b1 *
0"
1$
1#
#145000
0!
1"
