lab3/top_module_sig_anal6.v
module Analyse(
    input  wire clk,
    input  wire a,
    input  wire b,
    output reg q,
    output reg state
);
    
reg prev_a;
reg prev_b;


always @(*) begin
    case(state)
        0: q = a ^ b;  
        1: q = (~(a ^ b));  
        default: q = 0;
    endcase
end

always @(posedge clk) begin
    case(state)
        0: state <= (prev_a & prev_b);
        1: state <= (prev_a | prev_b);
        default: state <= 0;
    endcase
    prev_a <= a;
    prev_b <= b;
end
endmodule

lab3/top_module_sig_anal6_tb.v
`timescale 1ns / 1ps

module Analyse_tb;

    reg clk = 1;
    reg a, b;
    wire q, state;
	always #5 clk <= ~clk;
    Analyse an (
        .clk(clk),
        .a(a),
        .b(b),
        .state(state),
        .q(q)
    );
    initial begin
        $dumpfile("wave.vcd");
		$dumpvars(0, Analyse_tb);

        $display("Running testbench for two_of_four module...");
        $display("clk a | p q | Result");
        $display("-----------------------------");
        
        a <= 0;
        b <= 0;
        #40     //40
        a <= 0;
        b <= 1;
        #10     //50
        a <= 1;
        b <= 0;
        #10     //60
        a <= 1;
        b <= 1;
        #10     //70
        a <= 0;
        b <= 0;
        #10     //80
        a <= 1;
        b <= 1;
        #30     //110
        a <= 1;
        b <= 0;
        #10     //120
        a <= 0;
        b <= 1;
        #10     //130
        a <= 0;
        b <= 0;
        #30
        $display("-----------------------------");
        $finish;
    end

    initial begin
		$monitor("t<=%-4d: clk <= %d, a <= %d, b <= %d, q <= %d, state <= %d", $time, clk, a, b, q, state);
	end

endmodule

lab3/wave.vcd
$date
	Tue Nov  4 17:46:39 2025
$end
$version
	Icarus Verilog
$end
$timescale
	1ps
$end
$scope module Analyse_tb $end
$var wire 1 ! state $end
$var wire 1 " q $end
$var reg 1 # a $end
$var reg 1 $ b $end
$var reg 1 % clk $end
$scope module an $end
$var wire 1 # a $end
$var wire 1 $ b $end
$var wire 1 % clk $end
$var reg 1 & prev_a $end
$var reg 1 ' prev_b $end
$var reg 1 " q $end
$var reg 1 ! state $end
$upscope $end
$upscope $end
$enddefinitions $end
$comment Show the parameter values. $end
$dumpall
$end
#0
$dumpvars
x'
x&
1%
0$
0#
0"
x!
$end
#5000
0%
#10000
0'
0&
0!
1%
#15000
0%
#20000
1%
#25000
0%
#30000
1%
#35000
0%
#40000
1'
1"
1%
1$
#45000
0%
#50000
0'
1&
1%
0$
1#
#55000
0%
#60000
1'
0"
1%
1$
#65000
0%
#70000
1"
0'
0&
1!
1%
0$
0#
#75000
0%
#80000
0"
1'
1&
0!
1%
1$
1#
#85000
0%
#90000
1"
1!
1%
#95000
0%
#100000
1%
#105000
0%
#110000
0'
0"
1%
0$
#115000
0%
#120000
1'
0&
1%
1$
0#
#125000
0%
#130000
0'
1"
1%
0$
#135000
0%
#140000
0"
0!
1%
